[
   {
      "name": "development",
      "type": "mysql",
      "host": "mysql",
      "port": 3306,
      "username": "",
      "password": "",
      "database": "",
      "synchronize": false,
      "logging": true,
      "migrationsRun": true,
      "entities": [ "src/entity/**/*.ts" ],
      "migrations": [ "src/migration/**/*.ts" ],
      "subscribers": [ "src/subscriber/**/*.ts" ],
      "cli": {
         "entitiesDir": "src/entity",
         "migrationsDir": "src/migration",
         "subscribersDir": "src/subscriber"
      }
   },
   {
      "name": "test",
      "type": "mysql",
      "host": "mysql",
      "port": 3306,
      "username": "test",
      "password": "password",
      "database": "test",
      "synchronize": true,
      "logging": false,
      "dropSchema": true,
      "entities": [ "src/entity/**/*.ts" ],
      "migrations": [ "src/migration/**/*.ts" ],
      "subscribers": [ "src/subscriber/**/*.ts" ],
      "cli": {
         "entitiesDir": "src/entity",
         "migrationsDir": "src/migration",
         "subscribersDir": "src/subscriber"
      }
   }
]